<class>
<keyword> class </keyword>
<identifier> Bat </identifier>
<symbol> { </symbol>
<classVarDec>
<keyword> field </keyword>
<keyword> int </keyword>
<identifier> x </identifier>['Bat.x', 'var', 'field', 'int', 'defined', 0]
<symbol> , </symbol>
<identifier> y </identifier>['Bat.y', 'var', 'field', 'int', 'defined', 1]
<symbol> ; </symbol>
</classVarDec>
<classVarDec>
<keyword> field </keyword>
<keyword> int </keyword>
<identifier> width </identifier>['Bat.width', 'var', 'field', 'int', 'defined', 2]
<symbol> , </symbol>
<identifier> height </identifier>['Bat.height', 'var', 'field', 'int', 'defined', 3]
<symbol> ; </symbol>
</classVarDec>
<classVarDec>
<keyword> field </keyword>
<keyword> int </keyword>
<identifier> direction </identifier>['Bat.direction', 'var', 'field', 'int', 'defined', 4]
<symbol> ; </symbol>
</classVarDec>
<subroutineDec>
<keyword> constructor </keyword>function
<identifier> Bat </identifier>
<identifier> new </identifier>Bat.new
<symbol> ( </symbol>
<parameterList>
<keyword> int </keyword>
<identifier> Ax </identifier>['Bat.Ax', 'argument', 'argument', 'int', 'defined', 0]
<symbol> , </symbol>
<keyword> int </keyword>
<identifier> Ay </identifier>['Bat.Ay', 'var', 'argument', 'int', 'defined', 5]
<symbol> , </symbol>
<keyword> int </keyword>
<identifier> Awidth </identifier>['Bat.Awidth', 'var', 'argument', 'int', 'defined', 6]
<symbol> , </symbol>
<keyword> int </keyword>
<identifier> Aheight </identifier>['Bat.Aheight', 'var', 'argument', 'int', 'defined', 7]
</parameterList>
<symbol> ) </symbol>
<subroutineBody>
<symbol> { </symbol>
<statements>
<letStatement>
<keyword> let </keyword>
<identifier> x </identifier>
<symbol> = </symbol>
<expression>
<term>
<identifier> Ax </identifier>
</term>
</expression>
<symbol> ; </symbol>
</letStatement>
<letStatement>
<keyword> let </keyword>
<identifier> y </identifier>
<symbol> = </symbol>
<expression>
<term>
<identifier> Ay </identifier>
</term>
</expression>
<symbol> ; </symbol>
</letStatement>
<letStatement>
<keyword> let </keyword>
<identifier> width </identifier>
<symbol> = </symbol>
<expression>
<term>
<identifier> Awidth </identifier>
</term>
</expression>
<symbol> ; </symbol>
</letStatement>
<letStatement>
<keyword> let </keyword>
<identifier> height </identifier>
<symbol> = </symbol>
<expression>
<term>
<identifier> Aheight </identifier>
</term>
</expression>
<symbol> ; </symbol>
</letStatement>
<letStatement>
<keyword> let </keyword>
<identifier> direction </identifier>
<symbol> = </symbol>
<expression>
<term>
<integerConstant> 2 </integerConstant>
</term>
</expression>
<symbol> ; </symbol>
</letStatement>
<doStatement>
<keyword> do </keyword>
<identifier> show </identifier>Bat.show
<symbol> ( </symbol>
<expressionList>
</expressionList>
<symbol> ) </symbol>
<symbol> ; </symbol>
</doStatement>
<returnStatement>
<keyword> return </keyword>
<expression>
<term>
<keyword> this </keyword>
</term>
</expression>
<symbol> ; </symbol>
</returnStatement>
</statements>
<symbol> } </symbol>
</subroutineBody>
</subroutineDec>
<subroutineDec>
<keyword> method </keyword>function
<keyword> void </keyword>
<identifier> dispose </identifier>Bat.dispose
<symbol> ( </symbol>
<parameterList>
</parameterList>
<symbol> ) </symbol>
<subroutineBody>
<symbol> { </symbol>
<statements>
<doStatement>
<keyword> do </keyword>
<identifier> Memory </identifier>
<symbol> . </symbol>
<identifier> deAlloc </identifier>Bat.deAlloc
<symbol> ( </symbol>
<expressionList>
<expression>
<term>
<keyword> this </keyword>
</term>
</expression>
</expressionList>
<symbol> ) </symbol>
<symbol> ; </symbol>
</doStatement>
<returnStatement>
<keyword> return </keyword>
<symbol> ; </symbol>
</returnStatement>
</statements>
<symbol> } </symbol>
</subroutineBody>
</subroutineDec>
<subroutineDec>
<keyword> method </keyword>function
<keyword> void </keyword>
<identifier> show </identifier>Bat.show
<symbol> ( </symbol>
<parameterList>
</parameterList>
<symbol> ) </symbol>
<subroutineBody>
<symbol> { </symbol>
<statements>
<doStatement>
<keyword> do </keyword>
<identifier> Screen </identifier>
<symbol> . </symbol>
<identifier> setColor </identifier>Bat.setColor
<symbol> ( </symbol>
<expressionList>
<expression>
<term>
<keyword> true </keyword>
</term>
</expression>
</expressionList>
<symbol> ) </symbol>
<symbol> ; </symbol>
</doStatement>
<doStatement>
<keyword> do </keyword>
<identifier> draw </identifier>Bat.draw
<symbol> ( </symbol>
<expressionList>
</expressionList>
<symbol> ) </symbol>
<symbol> ; </symbol>
</doStatement>
<returnStatement>
<keyword> return </keyword>
<symbol> ; </symbol>
</returnStatement>
</statements>
<symbol> } </symbol>
</subroutineBody>
</subroutineDec>
<subroutineDec>
<keyword> method </keyword>function
<keyword> void </keyword>
<identifier> hide </identifier>Bat.hide
<symbol> ( </symbol>
<parameterList>
</parameterList>
<symbol> ) </symbol>
<subroutineBody>
<symbol> { </symbol>
<statements>
<doStatement>
<keyword> do </keyword>
<identifier> Screen </identifier>
<symbol> . </symbol>
<identifier> setColor </identifier>Bat.setColor
<symbol> ( </symbol>
<expressionList>
<expression>
<term>
<keyword> false </keyword>
</term>
</expression>
</expressionList>
<symbol> ) </symbol>
<symbol> ; </symbol>
</doStatement>
<doStatement>
<keyword> do </keyword>
<identifier> draw </identifier>Bat.draw
<symbol> ( </symbol>
<expressionList>
</expressionList>
<symbol> ) </symbol>
<symbol> ; </symbol>
</doStatement>
<returnStatement>
<keyword> return </keyword>
<symbol> ; </symbol>
</returnStatement>
</statements>
<symbol> } </symbol>
</subroutineBody>
</subroutineDec>
<subroutineDec>
<keyword> method </keyword>function
<keyword> void </keyword>
<identifier> draw </identifier>Bat.draw
<symbol> ( </symbol>
<parameterList>
</parameterList>
<symbol> ) </symbol>
<subroutineBody>
<symbol> { </symbol>
<statements>
<doStatement>
<keyword> do </keyword>
<identifier> Screen </identifier>
<symbol> . </symbol>
<identifier> drawRectangle </identifier>Bat.drawRectangle
<symbol> ( </symbol>
<expressionList>
<expression>
<term>
<identifier> x </identifier>
</term>
</expression>
<symbol> , </symbol>
<expression>
<term>
<identifier> y </identifier>
</term>
</expression>
<symbol> , </symbol>
<expression>
<term>
<identifier> x </identifier>
</term>
<symbol> + </symbol>
<term>
<identifier> width </identifier>
</term>
</expression>
<symbol> , </symbol>
<expression>
<term>
<identifier> y </identifier>
</term>
<symbol> + </symbol>
<term>
<identifier> height </identifier>
</term>
</expression>
</expressionList>
<symbol> ) </symbol>
<symbol> ; </symbol>
</doStatement>
<returnStatement>
<keyword> return </keyword>
<symbol> ; </symbol>
</returnStatement>
</statements>
<symbol> } </symbol>
</subroutineBody>
</subroutineDec>
<subroutineDec>
<keyword> method </keyword>function
<keyword> void </keyword>
<identifier> setDirection </identifier>Bat.setDirection
<symbol> ( </symbol>
<parameterList>
<keyword> int </keyword>
<identifier> Adirection </identifier>['Bat.Adirection', 'argument', 'argument', 'int', 'defined', 1]
</parameterList>
<symbol> ) </symbol>
<subroutineBody>
<symbol> { </symbol>
<statements>
<letStatement>
<keyword> let </keyword>
<identifier> direction </identifier>
<symbol> = </symbol>
<expression>
<term>
<identifier> Adirection </identifier>
</term>
</expression>
<symbol> ; </symbol>
</letStatement>
<returnStatement>
<keyword> return </keyword>
<symbol> ; </symbol>
</returnStatement>
</statements>
<symbol> } </symbol>
</subroutineBody>
</subroutineDec>
<subroutineDec>
<keyword> method </keyword>function
<keyword> int </keyword>
<identifier> getLeft </identifier>Bat.getLeft
<symbol> ( </symbol>
<parameterList>
</parameterList>
<symbol> ) </symbol>
<subroutineBody>
<symbol> { </symbol>
<statements>
<returnStatement>
<keyword> return </keyword>
<expression>
<term>
<identifier> x </identifier>
</term>
</expression>
<symbol> ; </symbol>
</returnStatement>
</statements>
<symbol> } </symbol>
</subroutineBody>
</subroutineDec>
<subroutineDec>
<keyword> method </keyword>function
<keyword> int </keyword>
<identifier> getRight </identifier>Bat.getRight
<symbol> ( </symbol>
<parameterList>
</parameterList>
<symbol> ) </symbol>
<subroutineBody>
<symbol> { </symbol>
<statements>
<returnStatement>
<keyword> return </keyword>
<expression>
<term>
<identifier> x </identifier>
</term>
<symbol> + </symbol>
<term>
<identifier> width </identifier>
</term>
</expression>
<symbol> ; </symbol>
</returnStatement>
</statements>
<symbol> } </symbol>
</subroutineBody>
</subroutineDec>
<subroutineDec>
<keyword> method </keyword>function
<keyword> void </keyword>
<identifier> setWidth </identifier>Bat.setWidth
<symbol> ( </symbol>
<parameterList>
<keyword> int </keyword>
<identifier> Awidth </identifier>['Bat.Awidth', 'argument', 'argument', 'int', 'defined', 2]
</parameterList>
<symbol> ) </symbol>
<subroutineBody>
<symbol> { </symbol>
<statements>
<doStatement>
<keyword> do </keyword>
<identifier> hide </identifier>Bat.hide
<symbol> ( </symbol>
<expressionList>
</expressionList>
<symbol> ) </symbol>
<symbol> ; </symbol>
</doStatement>
<letStatement>
<keyword> let </keyword>
<identifier> width </identifier>
<symbol> = </symbol>
<expression>
<term>
<identifier> Awidth </identifier>
</term>
</expression>
<symbol> ; </symbol>
</letStatement>
<doStatement>
<keyword> do </keyword>
<identifier> show </identifier>Bat.show
<symbol> ( </symbol>
<expressionList>
</expressionList>
<symbol> ) </symbol>
<symbol> ; </symbol>
</doStatement>
<returnStatement>
<keyword> return </keyword>
<symbol> ; </symbol>
</returnStatement>
</statements>
<symbol> } </symbol>
</subroutineBody>
</subroutineDec>
<subroutineDec>
<keyword> method </keyword>function
<keyword> void </keyword>
<identifier> move </identifier>Bat.move
<symbol> ( </symbol>
<parameterList>
</parameterList>
<symbol> ) </symbol>
<subroutineBody>
<symbol> { </symbol>
<statements>
<ifStatement>
<keyword> if </keyword>
<symbol> ( </symbol>
<expression>
<term>
<identifier> direction </identifier>
</term>
<symbol> = </symbol>
<term>
<integerConstant> 1 </integerConstant>
</term>
</expression>
<symbol> ) </symbol>
<symbol> { </symbol>
<statements>
<letStatement>
<keyword> let </keyword>
<identifier> x </identifier>
<symbol> = </symbol>
<expression>
<term>
<identifier> x </identifier>
</term>
<symbol> - </symbol>
<term>
<integerConstant> 4 </integerConstant>
</term>
</expression>
<symbol> ; </symbol>
</letStatement>
<ifStatement>
<keyword> if </keyword>
<symbol> ( </symbol>
<expression>
<term>
<identifier> x </identifier>
</term>
<symbol> &lt; </symbol>
<term>
<integerConstant> 0 </integerConstant>
</term>
</expression>
<symbol> ) </symbol>
<symbol> { </symbol>
<statements>
<letStatement>
<keyword> let </keyword>
<identifier> x </identifier>
<symbol> = </symbol>
<expression>
<term>
<integerConstant> 0 </integerConstant>
</term>
</expression>
<symbol> ; </symbol>
</letStatement>
</statements>
<symbol> } </symbol>
</ifStatement>
<doStatement>
<keyword> do </keyword>
<identifier> Screen </identifier>
<symbol> . </symbol>
<identifier> setColor </identifier>Bat.setColor
<symbol> ( </symbol>
<expressionList>
<expression>
<term>
<keyword> false </keyword>
</term>
</expression>
</expressionList>
<symbol> ) </symbol>
<symbol> ; </symbol>
</doStatement>
<doStatement>
<keyword> do </keyword>
<identifier> Screen </identifier>
<symbol> . </symbol>
<identifier> drawRectangle </identifier>Bat.drawRectangle
<symbol> ( </symbol>
<expressionList>
<expression>
<term>
<symbol> ( </symbol>
<expression>
<term>
<identifier> x </identifier>
</term>
<symbol> + </symbol>
<term>
<identifier> width </identifier>
</term>
</expression>
<symbol> ) </symbol>
</term>
<symbol> + </symbol>
<term>
<integerConstant> 1 </integerConstant>
</term>
</expression>
<symbol> , </symbol>
<expression>
<term>
<identifier> y </identifier>
</term>
</expression>
<symbol> , </symbol>
<expression>
<term>
<symbol> ( </symbol>
<expression>
<term>
<identifier> x </identifier>
</term>
<symbol> + </symbol>
<term>
<identifier> width </identifier>
</term>
</expression>
<symbol> ) </symbol>
</term>
<symbol> + </symbol>
<term>
<integerConstant> 4 </integerConstant>
</term>
</expression>
<symbol> , </symbol>
<expression>
<term>
<identifier> y </identifier>
</term>
<symbol> + </symbol>
<term>
<identifier> height </identifier>
</term>
</expression>
</expressionList>
<symbol> ) </symbol>
<symbol> ; </symbol>
</doStatement>
<doStatement>
<keyword> do </keyword>
<identifier> Screen </identifier>
<symbol> . </symbol>
<identifier> setColor </identifier>Bat.setColor
<symbol> ( </symbol>
<expressionList>
<expression>
<term>
<keyword> true </keyword>
</term>
</expression>
</expressionList>
<symbol> ) </symbol>
<symbol> ; </symbol>
</doStatement>
<doStatement>
<keyword> do </keyword>
<identifier> Screen </identifier>
<symbol> . </symbol>
<identifier> drawRectangle </identifier>Bat.drawRectangle
<symbol> ( </symbol>
<expressionList>
<expression>
<term>
<identifier> x </identifier>
</term>
</expression>
<symbol> , </symbol>
<expression>
<term>
<identifier> y </identifier>
</term>
</expression>
<symbol> , </symbol>
<expression>
<term>
<identifier> x </identifier>
</term>
<symbol> + </symbol>
<term>
<integerConstant> 3 </integerConstant>
</term>
</expression>
<symbol> , </symbol>
<expression>
<term>
<identifier> y </identifier>
</term>
<symbol> + </symbol>
<term>
<identifier> height </identifier>
</term>
</expression>
</expressionList>
<symbol> ) </symbol>
<symbol> ; </symbol>
</doStatement>
</statements>
<symbol> } </symbol>
<keyword> else </keyword>
<symbol> { </symbol>
<statements>
<letStatement>
<keyword> let </keyword>
<identifier> x </identifier>
<symbol> = </symbol>
<expression>
<term>
<identifier> x </identifier>
</term>
<symbol> + </symbol>
<term>
<integerConstant> 4 </integerConstant>
</term>
</expression>
<symbol> ; </symbol>
</letStatement>
<ifStatement>
<keyword> if </keyword>
<symbol> ( </symbol>
<expression>
<term>
<symbol> ( </symbol>
<expression>
<term>
<identifier> x </identifier>
</term>
<symbol> + </symbol>
<term>
<identifier> width </identifier>
</term>
</expression>
<symbol> ) </symbol>
</term>
<symbol> &gt; </symbol>
<term>
<integerConstant> 511 </integerConstant>
</term>
</expression>
<symbol> ) </symbol>
<symbol> { </symbol>
<statements>
<letStatement>
<keyword> let </keyword>
<identifier> x </identifier>
<symbol> = </symbol>
<expression>
<term>
<integerConstant> 511 </integerConstant>
</term>
<symbol> - </symbol>
<term>
<identifier> width </identifier>
</term>
</expression>
<symbol> ; </symbol>
</letStatement>
</statements>
<symbol> } </symbol>
</ifStatement>
<doStatement>
<keyword> do </keyword>
<identifier> Screen </identifier>
<symbol> . </symbol>
<identifier> setColor </identifier>Bat.setColor
<symbol> ( </symbol>
<expressionList>
<expression>
<term>
<keyword> false </keyword>
</term>
</expression>
</expressionList>
<symbol> ) </symbol>
<symbol> ; </symbol>
</doStatement>
<doStatement>
<keyword> do </keyword>
<identifier> Screen </identifier>
<symbol> . </symbol>
<identifier> drawRectangle </identifier>Bat.drawRectangle
<symbol> ( </symbol>
<expressionList>
<expression>
<term>
<identifier> x </identifier>
</term>
<symbol> - </symbol>
<term>
<integerConstant> 4 </integerConstant>
</term>
</expression>
<symbol> , </symbol>
<expression>
<term>
<identifier> y </identifier>
</term>
</expression>
<symbol> , </symbol>
<expression>
<term>
<identifier> x </identifier>
</term>
<symbol> - </symbol>
<term>
<integerConstant> 1 </integerConstant>
</term>
</expression>
<symbol> , </symbol>
<expression>
<term>
<identifier> y </identifier>
</term>
<symbol> + </symbol>
<term>
<identifier> height </identifier>
</term>
</expression>
</expressionList>
<symbol> ) </symbol>
<symbol> ; </symbol>
</doStatement>
<doStatement>
<keyword> do </keyword>
<identifier> Screen </identifier>
<symbol> . </symbol>
<identifier> setColor </identifier>Bat.setColor
<symbol> ( </symbol>
<expressionList>
<expression>
<term>
<keyword> true </keyword>
</term>
</expression>
</expressionList>
<symbol> ) </symbol>
<symbol> ; </symbol>
</doStatement>
<doStatement>
<keyword> do </keyword>
<identifier> Screen </identifier>
<symbol> . </symbol>
<identifier> drawRectangle </identifier>Bat.drawRectangle
<symbol> ( </symbol>
<expressionList>
<expression>
<term>
<symbol> ( </symbol>
<expression>
<term>
<identifier> x </identifier>
</term>
<symbol> + </symbol>
<term>
<identifier> width </identifier>
</term>
</expression>
<symbol> ) </symbol>
</term>
<symbol> - </symbol>
<term>
<integerConstant> 3 </integerConstant>
</term>
</expression>
<symbol> , </symbol>
<expression>
<term>
<identifier> y </identifier>
</term>
</expression>
<symbol> , </symbol>
<expression>
<term>
<identifier> x </identifier>
</term>
<symbol> + </symbol>
<term>
<identifier> width </identifier>
</term>
</expression>
<symbol> , </symbol>
<expression>
<term>
<identifier> y </identifier>
</term>
<symbol> + </symbol>
<term>
<identifier> height </identifier>
</term>
</expression>
</expressionList>
<symbol> ) </symbol>
<symbol> ; </symbol>
</doStatement>
</statements>
<symbol> } </symbol>
</ifStatement>
<returnStatement>
<keyword> return </keyword>
<symbol> ; </symbol>
</returnStatement>
</statements>
<symbol> } </symbol>
</subroutineBody>
</subroutineDec>
<symbol> } </symbol>
</class>